{
    "Job ID": "4403330",
    "Description": "مطلوب موظفين عن بعد لمشروع جديد بتعاون مع وزارة العمل و التنمية\nالاعلان موجه للرجال و النساء,\nالعمل عن بعد ويتطلب منك :\n\n. استلام دفعات ,حوالات بنكية من العملاء وإيداعها الى الجهة المختصة.\n. الاحتفاظ بالوثائق والمستندات والفواتير الخاصة بالمبيعات.\n.إعداد التقارير حول عمليات البيع ورفع التقارير حول عمليات الصندوق اليومية.\n.معرفة العمل على الحاسوب و المواقع الاكترونيه.\n. قدره العمل تحت ضغط و انهاء مهام خلال الوقت المحدد.\n\nيجب اجتياز فتره تدريبيه قصيرة من قبل المسؤول على الطاقم. \nالمنصب تابع لقسم الماليه ويعتبر منصب اداري.\nراتب عالي + عمولة على المبيعات.\nسيتم الرد على المتقدمين المناسبين فقط.Skills",
    "Skills": [
        "المهارات بالعمل على الحاسوب و استعمال المواقع الاكترونيه .\nالعمل تحت ضغط.\nمهارات التفاوض.\nالامانة و المواضبة"
    ],
    "Preferred": {
        "Career Level": "Mid Career",
        "Years of Experience": "Min: 1",
        "Residence Location": "Saudi Arabia",
        "Age": "Min: 21"
    },
    "Data": {
        "Job Location": "Khamis Mushait, Saudi Arabia",
        "Company Industry": "Internet & E-commerce",
        "Company Type": "Employer (Private Sector)",
        "Job Role": "Administration",
        "Employment Type": "Freelancer",
        "Monthly Salary Range": "$6,000 - $7,000",
        "Number of Vacancies": "Unspecified"
    }
}