{
    "Job ID": "4622875",
    "Description": "Auto Technician Level 2-3 (Ford)Job ResponsibilitiesPerform Line Technician Services\nRoutine Inspections/Maintenance\nSystem Diagnostics\nFull Automotive Troubleshooting and Testing\nContinuously expanding your knowledge for new technologies and practiceSkills",
    "Skills": [
        "Job Qualifications",
        "Automotive dealership experience is preferred.\nMust-Have Tools\nGreat Mechanical Skills"
    ],
    "Preferred": {
        "Residence Location": "Qatar"
    },
    "Data": {
        "Job Location": "Qatar",
        "Company Industry": "Accounting",
        "Company Type": "Employer (Private Sector)",
        "Job Role": "Maintenance, Repair, and Technician",
        "Employment Type": "Full Time Employee",
        "Monthly Salary Range": "Unspecified",
        "Number of Vacancies": "1"
    }
}