{
    "Job ID": "4735530",
    "Description": "Manage information technology and computer systems.\nManage IT staff by recruiting, training and coaching employees, communicating job expectations and appraising their performance.\nDevelop information technology strategies and services in line with the organisation's overall strategy and objectives.\nDesign, develop, implement and coordinate systems, policies and procedures.\nEnsure security of data, network access and backup systems.\nResolve real-time issues and problems of important stakeholders with a well-planned system.Skills",
    "Skills": [
        "Experienced professional in the field of IT with an in-depth knowledge of managing a company's computer systems.\nExcellent knowledge of technical management, information analysis and of computer hardware/software systems.\nPossess in-depth knowledge of handling all network system requirements of a company.\nSkilled professional with a technical degree in the field of IT from a reputed institute.\nAbility to work in a diverse project team to develop an efficient and valuable IT solution.\nCommendable grasp of fluent communication and time management for organizing projects using a streamlined approach."
    ],
    "Preferred": {
        "Years of Experience": "Min: 5",
        "Age": "Min: 26 Max: 38"
    },
    "Data": {
        "Job Location": "Cairo, Egypt",
        "Company Industry": "Catering, Food Service, & Restaurant",
        "Company Type": "Unspecified",
        "Job Role": "Information Technology",
        "Employment Type": "Full Time Employee",
        "Monthly Salary Range": "Unspecified",
        "Number of Vacancies": "1"
    }
}