{
    "Job ID": "4740285",
    "Description": "Greet clients and visitors with a positive, helpful attitude.\nAssisting clients in finding their way around the office.\nMaintain workplace security by issuing, checking, and collecting badges as necessary and maintaining visitor logs.\nAssisting with a variety of administrative tasks including copying, faxing, taking notes, and making travel plans.\nPreparing meeting and training rooms.\nAnswering phones in a professional manner, and routing calls as necessary.\nAssisting colleagues with administrative tasks.\nPerforming ad-hoc administrative duties.\nAnswering, forwarding, and screening phone calls.\nProvide excellent customer service.\nScheduling appointments.Skills",
    "Skills": [
        "Bachelor’s degree in a related field.\nFresher or with one year experience in the related field.\nSaudi National.\nConsistent, professional dress, and manner.\nExcellent written and verbal communication skills in English.\nCompetency in Microsoft applications including Word, Excel, and Outlook.\nGood time management skills.\nExperience with administrative and clerical procedures.\nAble to contribute positively as part of a team, helping with various tasks as required."
    ],
    "Preferred": {
        "Residence Location": "Riyadh, Saudi Arabia",
        "Nationality": "Saudi Arabia",
        "Degree": "Bachelor's degree / higher diploma",
        "Age": "Min: 18 Max: 35"
    },
    "Data": {
        "Job Location": "Riyadh, Saudi Arabia",
        "Company Industry": "Project & Construction Planning",
        "Company Type": "Employer (Private Sector)",
        "Job Role": "Administration",
        "Employment Type": "Full Time Employee",
        "Monthly Salary Range": "Unspecified",
        "Number of Vacancies": "1"
    }
}