{
    "Job ID": "4741834",
    "Description": "Leverage social media trends to advertise and highlight different ongoing activities of the company.\nIndulge in research and creation of engaging content for publishing on different online channels.\nWork with content creators, graphic designers, and other professionals to plan a successful social media strategy.\nEvaluate the outcome of online campaigns through real-time metrics and relevant tools.\nUse SEO analysis tools and software to track customer satisfaction, engagement, and ROI, suggesting appropriate optimization.\nStay up to date with the latest social media best practices and technologies.Skills",
    "Skills": [
        "Thorough knowledge of social media indicators like clicks, profile visits, likes, reach, etc.\nProficient in collaborating with relevant professionals to develop successful social media campaigns.\nProven track record of published content as a writer, blogger, or social media handler.\nPossessing remarkable potential in showcasing ideas through formal and informal modes.\nPositive attitude, detail, and customer-oriented with good multitasking and organizational ability."
    ],
    "Preferred": {
        "Residence Location": "Netherlands"
    },
    "Data": {
        "Job Location": "Amsterdam, Netherlands",
        "Company Industry": "Human Resources Outsourcing; Virtual Assistant Services; Internet & E-commerce",
        "Company Type": "Unspecified",
        "Job Role": "Marketing and PR",
        "Employment Type": "Part Time Employee",
        "Monthly Salary Range": "$4,000 - $5,000",
        "Number of Vacancies": "Unspecified"
    }
}