{
    "Job ID": "4742818",
    "Description": "Required Skills to be SuccessfulCommunication TeamworkAbout the TeamThe FM team is highly motivated, collaborative, and fun, Finance professionals across Egypt, looking to add an Admin to the department. What equips you for the role Bachelor's degree in Accounting or Business administration, or any related field.\nExperience of 0 - 2 years in Collections & Invoices.\nProficient Use of MS Applications.Job Details",
    "Skills": [],
    "Preferred": {},
    "Data": {
        "Job Location": "Egypt",
        "Company Industry": "Accounting",
        "Company Type": "Employer (Private Sector)",
        "Job Role": "Support Services",
        "Employment Type": "Full Time Employee",
        "Monthly Salary Range": "Unspecified",
        "Number of Vacancies": "1"
    }
}