{
    "Job ID": "4743558",
    "Description": "to provide timely support to the team and team leader for the monthly report submission.\nto verify the authorizations for asset acquisitions, check budget availability, capitalization, monthly depreciation, reports to management, asset book value, addition, sales of fixed asset, scraping.\nto ensure the monthly reconciliation of related party, interest charging, distribution and booking of centralized expenses, management fee etc.,\nto record all addition and deletion of general and employees' insurance viz PAR, Medical, Marine, Workmen Compensation, EEI policies etc.,\nto verify and record all administration and selling expenses, interdepartmental and inter-company.\nEnsure the accrual basis of accounting, real time and appropriate bookings of transactions. (Maintaining the accrual and prepayment account details account details).\nto ensure monthly clearing and monitoring of all internal customer and contra accounts.\nrecords the receipts from warranty claim, reconcile the manufacturer's warranty account in quarterly basis.\nbook all rental expenses, lease liability and rental income based on the valid contact/LPO.\nyearly bookings of ESB and Air Ticket provision to the employees account.Skills",
    "Skills": [
        "AGE limit between 25-40 years old\nBachelor Degree holder of Accounting or any related course\nFinance related training certificates is an advantage\nSAP experience is essential"
    ],
    "Preferred": {
        "Years of Experience": "Min: 3",
        "Residence Location": "Qatar",
        "Degree": "Bachelor's degree / higher diploma"
    },
    "Data": {
        "Job Location": "Doha, Qatar",
        "Company Industry": "Automotive Dealership & Distributor",
        "Company Type": "Employer (Private Sector)",
        "Job Role": "Accounting and Auditing",
        "Employment Type": "Full Time Employee",
        "Monthly Salary Range": "Unspecified",
        "Number of Vacancies": "1"
    }
}