{
    "Job ID": "4744670",
    "Description": "استقبال العملاء عند الدخول او الخروج من المتجر.\nإدارة المعاملات مع العملاء باستخدام السجلات النقدية.\nمراجعة وفحص البضائع والتأكد من دقة التسعير.\nجرد وجمع المدفوعات سواء نقدا أو باستخدام بطاقات الائتمان.\nإصدار الإيصالات أو المبالغ المستردة أو التغيير.\nاستبدال الكوبونات وقسائم الشراء.\nاجادة استخدام ملحقات الكمبيوتر المختلفة مثل اجهزة طباعة الفواتير وأجهزة قراءة اكواد المنتجات.\nالقدرة على استخدام برامج قواعد البيانات.\nاجادة مهارات جيدة في الرياضيات.\nامتلاك مهارات التواصل مع الشخصيات المختلفة.\nالقدرة على ترتيب المهام وادارة الوقت بشكل مميز.\nالعمل على اكتساب ثقة ورضا العملاء.Skills",
    "Skills": [
        "فوديكس"
    ],
    "Preferred": {},
    "Data": {
        "Job Location": "Dammam, Saudi Arabia",
        "Company Industry": "Catering, Food Service, & Restaurant",
        "Company Type": "Unspecified",
        "Job Role": "Finance and Investment",
        "Employment Type": "Full Time Employee",
        "Monthly Salary Range": "Unspecified",
        "Number of Vacancies": "1"
    }
}