{
    "Job ID": "4758321",
    "Description": "BASIC QUALIFICATIONS- Experience managing medium to large teams.- Experience working with data analysis and/or making decisions based on analysis.PREFERRED QUALIFICATIONS- If you are engaging, innovative, supportive, problem solver, and you worked in fast paced environments we want to hear from you!Job Details",
    "Skills": [],
    "Preferred": {},
    "Data": {
        "Job Location": "Abha, Saudi Arabia",
        "Company Industry": "Accounting",
        "Company Type": "Employer (Private Sector)",
        "Job Role": "Management",
        "Employment Type": "Full Time Employee",
        "Monthly Salary Range": "Unspecified",
        "Number of Vacancies": "1"
    }
}