{
    "Job ID": "4759508",
    "Description": "KEY REQUIREMENTSPossess a diploma in sales & marketing from a recognized institution.\nMinimum 03 years of sales experience preferably 1-2 years in the same industry.\nPossess good negotiation skills and ability to perform in tough market conditions.\nShould possess a valid riding / Driving license.\nPerformance driven and effective team player.Job Details",
    "Skills": [],
    "Preferred": {},
    "Data": {
        "Job Location": "Sri Lanka",
        "Company Industry": "Accounting",
        "Company Type": "Employer (Private Sector)",
        "Job Role": "Sales",
        "Employment Type": "Full Time Employee",
        "Monthly Salary Range": "Unspecified",
        "Number of Vacancies": "1"
    }
}