{
    "Job ID": "4760676",
    "Description": "Required skills to be successful:Job-Specific Skills:Knowledge in 2D & 3D design – Proficient in AutoCAD, 3D software such as 3DS Max, Vray, SketchUp.\nKnowledge of Photoshop, InDesign and other image editing / rendering software\nKnowledge of the design process, including M&E and detail construction drawings, colour & materials, furniture and carpentry systems, specifications, and detailing will be a plus.\nExcellent interpersonal and communication skills, self-motivated, hardworking, willing to work independently and as a team.\nShould have Knowledge in Interior Designing/Joinery/ Fit Out Industry\nKnowledge in Space Planning & Commercial Interior Environment, Fit out detailing, Specifications.\nStrong knowledge of MEP and Electrical works technicalities and drawings\nStrong knowledge of UAE construction code and technical files.\nKnowledge of Quantifying the Material What equips you for the role:Minimum Qualifications, Certification and Knowledge: Diploma in Interior Design / Civil Engineering. \nUnderstanding of local market and knowledge of Public Entities, contractors and vendors.\nGood Understanding of Fitout / Civil contracts. Minimum Experience:10 years' experience in a related field of which 5 years are in a similar capacity in the Civil / Fit out Contracting companies. Job Details",
    "Skills": [],
    "Preferred": {},
    "Data": {
        "Job Location": "Dubai, United Arab Emirates",
        "Company Industry": "Accounting",
        "Company Type": "Employer (Private Sector)",
        "Job Role": "Civil Engineering",
        "Employment Type": "Full Time Employee",
        "Monthly Salary Range": "Unspecified",
        "Number of Vacancies": "1"
    }
}