{
    "Job ID": "4760759",
    "Description": "Provide leadership and Drilling &WorkOver completion engineering oversight in the selection of the single preferred completion type, Wellhead design, and the associated detailed engineering that will be easily understood and actioned by the Engineering & Operation Team to deliver the agreed well objectives.Review drilling/workover completion programs for all wells of Offshore Fields to ensure they meet well proposal objectives.Preparing completion cost estimates and assessing risk in terms of probability and potential remedies.Skills",
    "Skills": [
        "Minimum 12 years of experience in Completion Engineering principal and intelligent completion and wellhead"
    ],
    "Preferred": {
        "Years of Experience": "Min: 12 Max: 20",
        "Gender": "Male",
        "Degree": "Bachelor's degree / higher diploma",
        "Age": "Min: 35 Max: 55"
    },
    "Data": {
        "Job Location": "Eastern Province, Saudi Arabia",
        "Company Industry": "Oil & Gas",
        "Company Type": "Employer (Private Sector)",
        "Job Role": "Engineering",
        "Employment Type": "Full Time Employee",
        "Monthly Salary Range": "Unspecified",
        "Number of Vacancies": "1"
    }
}