{
    "Job ID": "69856896",
    "Description": "Clinical Nurse Facilitator (Women’s Services) \"Job Details\"Job DescriptionJOB SUMMARYKEY ROLE ACCOUNTABILITIES////In view of the evolving needs and opportunities within Sidra, this position may be required to perform other duties as assigned and reporting relationships may vary.QUALIFICATIONS, EXPERIENCE AND SKILLS – SELECTION CRITERIAESSENTIALPREFERREDJob Details",
    "Skills": [],
    "Preferred": {},
    "Data": {
        "Job Location": "Qatar",
        "Company Industry": "Other Business Support Services",
        "Company Type": "Employer (Private Sector)",
        "Employment Type": "Unspecified",
        "Monthly Salary Range": "Unspecified",
        "Number of Vacancies": "Unspecified"
    }
}