{
    "Job ID": "69866247",
    "Description": "Job Details:We are looking forward to candidates with:  Experience in SoC  Verification  Knowledge in DFX, design for test, debug, and manufacturing.  Experience in post-Si validation/debug  Experience in SOC or IP verification  UVM/OVM testbench knowledge  Good understanding of SoC architecture / uArchitecture  Strong analytical ability, problem solving and communication skills  Facilitator of direct and open communication, diversity of opinion, and debate.  Ability to work independently and at various levels of abstractionQualifications:Qualifications:Experience : 3-10yrs experience with following proficiencies:Bachelor Degree in Electrical and Electronics Engineering or Master Degree in Electrical and Electronics Engineering or Computer EngineeringStrong Communications skills and the ability to effectively work with cross functional teams.Work Model for this RoleJob Details",
    "Skills": [],
    "Preferred": {},
    "Data": {
        "Job Location": "Bengaluru, India",
        "Company Industry": "Other Business Support Services",
        "Company Type": "Unspecified",
        "Employment Type": "Unspecified",
        "Monthly Salary Range": "Unspecified",
        "Number of Vacancies": "Unspecified"
    }
}