{
    "Job ID": "69867250",
    "Description": "Working closely with the BI and technical team to give our customer a WoW checkout experience by developing short and long-term product strategies and technical roadmaps.\nWhile always placing the customer first, drive a global strategy to serve both our end users: the customer and the shopper.\nDevelop and managing customer success metrics through collaborating with BI, UX and technical team.\nUnderstand markets, competition and user pain points in depth\nManage annual and quarterly product OKRs.\nLook at a problem space for a team scope autonomously and identify problems through quantitative and qualitative research.\nBreak complex problem statements into smaller chunks and lead the team into smaller iterative deliveries.\nDeliver roadmaps based on strategies and able to pivot on a strategic direction.\nAlign C-Level leadership and different stakeholders towards a specific direction or a certain feature.\nMentor junior PM’s and establish shared vision across the company by building consensus on priorities leading to product execution.\nRun SCRUM/KANBAN meetings and Stand-ups and maintain the AGILE methodologies.Job Details",
    "Skills": [],
    "Preferred": {},
    "Data": {
        "Job Location": "Cairo, Egypt",
        "Company Industry": "Other Business Support Services",
        "Company Type": "Unspecified",
        "Employment Type": "Unspecified",
        "Monthly Salary Range": "Unspecified",
        "Number of Vacancies": "Unspecified"
    }
}