{"Job ID": "69872928", "Description": "Solutions CoordinatorDescriptionSupports sales force through reporting, system administration and internal & external data analyses by executing and supporting selected activities under limited supervision.Reporting:Consolidates and distributes sales reports where reporting tasks are repetitive and well documented, under limited supervision.Gathers and consolidates data from others through existing templates and provides as forecasting input.System Administration:Runs repetitive and ad-hoc tasks on systems and tools (e.g. salesforce, WWSPS, BMS, Portal).Periodically reviews the user-entered data hosted on the systems to ensure completeness under limited supervision.Data Analyses (Internal & external):Conducts ad-hoc and repetitive analyses on external sources (e.g. Polk, Dodge, RigDig, etc.).Researches assigned opportunities through secondary research, compiles and shares findings.Compiles relevant competitive data from varying resources under limited supervision.Conducts internal sales analyses (e.g. variances, projections, costing, bundling) where the tasks are well documented.QualificationsSkillsCommunicates effectively - Developing and delivering multi-mode communications that convey a clear understanding of the unique needs of different audiences.Action oriented - Taking on new opportunities and tough challenges with a sense of urgency, high energy, and enthusiasm.Customer focus - Building strong customer relationships and delivering customer-centric solutions.Collaborates - Building partnerships and working collaboratively with others to meet shared objectives.Education, Licenses, CertificationsHigh school diploma or certificate of completion of secondary education or equivalent experience to the extent such experience meets applicable regulations.This position may require licensing for compliance with export controls or sanctions regulations.ExperienceRequires some work experience and intermediate level knowledge obtained through training or on-the-job experience.-Evaluation of service reports, delivery challans & purchase order to send accurate billing instructions for invoice generationUnderstand individual customer processes & ensure Invoice submission with appropriate documents\n\nTimely & persistent payment follow-up to ensure collection of payment as per due date-Basic MS office (Word, Excel, Power Point), meet weekly & monthly BI submission and payment collection targets, work with various stake holders for issue resolution-Knowledge on after market service support and fluent spoken Telugu language would be added advantageJob SALESPrimary Location India-Andhra Pradesh-Hyderabad-India, Hyderabad, DBU Area OfficeJob Type Experienced - Exempt / OfficeRecruitment Job Type OfficeJob Posting Sep 15, 2023, 3:23:06 AMUnposting Date OngoingOrganization Distribution BusinessRole Category Hybrid - Potential for Partial RemoteRelocation Package EligibleReq ID: 230008ZEJob Details", "Skills": [], "Preferred": {}, "Data": {"Job Location": "Hyderabad, Pakistan", "Company Industry": "Other Business Support Services", "Company Type": "Unspecified", "Employment Type": "Unspecified", "Monthly Salary Range": "Unspecified", "Number of Vacancies": "Unspecified", "Job Role": "Unspecified"}}